theia/__init__.py
theia/collector.py
theia/comm.py
theia/metadata.py
theia/model.py
theia/naivestore.py
theia/query.py
theia/storeapi.py
theia/watcher.py
theia/cli/__init__.py
theia/cli/__main__.py
theia/cli/collector.py
theia/cli/parser.py
theia/cli/query.py
theia/cli/simulate.py
theia/cli/tau.py
theia/cli/watcher.py
theia-0.9.1.dist-info/METADATA
theia-0.9.1.dist-info/RECORD
theia-0.9.1.dist-info/WHEEL
theia-0.9.1.dist-info/top_level.txt
