Metadata-Version: 2.1
Name: theia
Version: 0.9.1
Summary: Theia is a lightweight log aggregator.
Home-page: https://github.com/theia-log/theia
Author: Pavle Jonoski
Author-email: jonoski.pavle@gmail.com
License: UNKNOWN
Platform: UNKNOWN
Classifier: Programming Language :: Python :: 3
Classifier: Development Status :: 3 - Alpha
Classifier: Intended Audience :: Developers
Classifier: Intended Audience :: System Administrators
Classifier: License :: OSI Approved :: Apache Software License
Classifier: Topic :: Internet :: Log Analysis
Classifier: Topic :: Software Development :: Libraries
Classifier: Topic :: System :: Logging
Classifier: Topic :: Utilities
Requires-Dist: pathtools (==0.1.2)
Requires-Dist: picotui (==0.9.1)
Requires-Dist: PyYAML (==3.12)
Requires-Dist: watchdog (==0.8.3)
Requires-Dist: websockets (==3.3)
